vaiskit/__init__.py
vaiskit/vais.py
vaiskit/nlp/__init__.py
vaiskit/nlp/v1/__init__.py
vaiskit/nlp/v1/cloud_nlp_pb2.py
vaiskit/nlp/v1/cloud_nlp_pb2_grpc.py
vaiskit/speech/__init__.py
vaiskit/speech/v1/__init__.py
vaiskit/speech/v1/cloud_speech_pb2.py
vaiskit/speech/v1/cloud_speech_pb2_grpc.py
vaiskit-0.1.0.dist-info/DESCRIPTION.rst
vaiskit-0.1.0.dist-info/METADATA
vaiskit-0.1.0.dist-info/RECORD
vaiskit-0.1.0.dist-info/WHEEL
vaiskit-0.1.0.dist-info/metadata.json
vaiskit-0.1.0.dist-info/top_level.txt
