Metadata-Version: 2.0
Name: vaiskit
Version: 0.1.0
Summary: UNKNOWN
Home-page: https://vais.vn
Author: VAIS
Author-email: support@vais.vn
License: UNKNOWN
Platform: UNKNOWN
Requires-Python: >=2.6, !=3.0.*, !=3.1.*, !=3.2.*, <4
Requires-Dist: grpcio (==1.4.0)
Requires-Dist: pyaudio (==0.2.11)
